cli.py
simple_tf_linter/__init__.py
simple_tf_linter/compare_path.py
simple_tf_linter/iterate_dict.py
simple_tf_linter/key_value_rule.py
simple_tf_linter/linter_basic.py
SimpleTFLinter-0.2.2.dist-info/LICENSE
SimpleTFLinter-0.2.2.dist-info/METADATA
SimpleTFLinter-0.2.2.dist-info/WHEEL
SimpleTFLinter-0.2.2.dist-info/entry_points.txt
SimpleTFLinter-0.2.2.dist-info/top_level.txt
SimpleTFLinter-0.2.2.dist-info/RECORD
