Metadata-Version: 2.1
Name: SimpleTFLinter
Version: 0.2.2
Summary: Simple Terraform Linter is a lightweight command-line tool for checking Terraform configuration files against custom rules. It supports input from Terraform folders or JSON files, with easy customization and extensibility through user-defined rules defined in YAML files.
Home-page: https://github.com/AutomationLover/TerraformLinter
Author: William Wang
Author-email: williamwangatsydney@gmail.com
License: UNKNOWN
Platform: UNKNOWN
Classifier: Development Status :: 3 - Alpha
Classifier: Intended Audience :: Developers
Classifier: License :: OSI Approved :: MIT License
Classifier: Programming Language :: Python :: 3
Classifier: Programming Language :: Python :: 3.6
Classifier: Programming Language :: Python :: 3.7
Classifier: Programming Language :: Python :: 3.8
Classifier: Programming Language :: Python :: 3.9
Classifier: Programming Language :: Python :: 3.10
Requires-Python: >=3.6
License-File: LICENSE
Requires-Dist: python-hcl2
Requires-Dist: PyYAML
Requires-Dist: pytest
Requires-Dist: twine
